README.md
setup.cfg
setup.py
fkl/__init__.py
fkl/fkl_basic.py
fkl/fkl_function.py
fkl/fkl_function_pool.py
fkl/fkl_io.py
fkl/fkl_math.py
fkl/fkl_model.py
fkl/fkl_process_pool.py
fkl/fkl_socket.py
fkl/fkl_socket_connect.py
fkl/fkl_string.py
fkl/fkl_thread_lock.py
fkl/fkl_thread_pool.py
fkl/fkl_time.py
fkl.egg-info/PKG-INFO
fkl.egg-info/SOURCES.txt
fkl.egg-info/dependency_links.txt
fkl.egg-info/top_level.txt