Metadata-Version: 1.0
Name: fkl
Version: 1.0.5.3
Summary: This is a lightweight library written by python3
Home-page: https://github.com/k12501599501/fk_lib
Author: k12501599501
Author-email: k12501599501@gmail.com
License: MIT License
Keywords: fkl
Platform: any
